openrag_sdk/__init__.py
openrag_sdk/chat.py
openrag_sdk/client.py
openrag_sdk/documents.py
openrag_sdk/exceptions.py
openrag_sdk/knowledge_filters.py
openrag_sdk/models.py
openrag_sdk/search.py
openrag_sdk-0.1.2.dist-info/METADATA
openrag_sdk-0.1.2.dist-info/WHEEL
openrag_sdk-0.1.2.dist-info/top_level.txt
openrag_sdk-0.1.2.dist-info/RECORD
