Metadata-Version: 2.4
Name: openrag-sdk
Version: 0.1.2
Summary: Official Python SDK for OpenRAG API
Author: OpenRAG Team
License-Expression: MIT
Project-URL: Homepage, https://github.com/langflow-ai/openrag
Project-URL: Documentation, https://docs.openr.ag/sdk/python
Project-URL: Repository, https://github.com/langflow-ai/openrag
Project-URL: Issues, https://github.com/langflow-ai/openrag/issues
Keywords: openrag,rag,retrieval,ai,sdk,api
Classifier: Development Status :: 4 - Beta
Classifier: Intended Audience :: Developers
Classifier: Programming Language :: Python :: 3
Classifier: Programming Language :: Python :: 3.10
Classifier: Programming Language :: Python :: 3.11
Classifier: Programming Language :: Python :: 3.12
Classifier: Programming Language :: Python :: 3.13
Classifier: Topic :: Software Development :: Libraries :: Python Modules
Classifier: Typing :: Typed
Requires-Python: >=3.10
Requires-Dist: httpx>=0.25.0
Requires-Dist: pydantic>=2.0.0
Provides-Extra: dev
Requires-Dist: pytest>=7.0.0; extra == "dev"
Requires-Dist: pytest-asyncio>=0.21.0; extra == "dev"
